LICENSE
MANIFEST.in
README.rst
setup.cfg
setup.py
handwritingio/__init__.py
handwritingio/version.py
handwritingio.egg-info/PKG-INFO
handwritingio.egg-info/SOURCES.txt
handwritingio.egg-info/dependency_links.txt
handwritingio.egg-info/requires.txt
handwritingio.egg-info/top_level.txt
test/conftest.py
test/test_client.py
test/test_decode.py