Metadata-Version: 1.1
Name: handwritingio
Version: 1.0.0
Summary: Handwriting.io API client.
Home-page: https://github.com/handwritingio/python-client
Author: Handwriting.io
Author-email: support@handwriting.io
License: MIT License
Platform: UNKNOWN
Classifier: Intended Audience :: Developers
Classifier: Natural Language :: English
Classifier: License :: OSI Approved :: MIT License
Classifier: Programming Language :: Python
Classifier: Programming Language :: Python :: 2.7
Classifier: Programming Language :: Python :: 3
Classifier: Programming Language :: Python :: 3.4
Classifier: Programming Language :: Python :: 3.5
